LICENSE
MANIFEST.in
README.rst
requirements.txt
setup.py
src/ezrsa/__init__.py
src/ezrsa/admin.py
src/ezrsa/apps.py
src/ezrsa/models.py
src/ezrsa/services.py
src/ezrsa/tests.py
src/ezrsa/urls.py
src/ezrsa/utils.py
src/ezrsa/views.py
src/ezrsa.egg-info/PKG-INFO
src/ezrsa.egg-info/SOURCES.txt
src/ezrsa.egg-info/dependency_links.txt
src/ezrsa.egg-info/not-zip-safe
src/ezrsa.egg-info/requires.txt
src/ezrsa.egg-info/top_level.txt
src/ezrsa/locale/zh_Hans/LC_MESSAGES/django.mo
src/ezrsa/locale/zh_Hans/LC_MESSAGES/django.po
src/ezrsa/migrations/0001_initial.py
src/ezrsa/migrations/__init__.py