Metadata-Version: 1.1
Name: ezrsa
Version: 0.1.1
Summary: Easy Rsa Django Application
Home-page: https://github.com/appstore-zencore/ezrsa
Author: Appstore Zencore
Author-email: appstore@zencore.cn
License: MIT
Keywords: ezrsa
Platform: UNKNOWN
Classifier: Development Status :: 5 - Production/Stable
Classifier: Intended Audience :: Developers
Classifier: Topic :: Software Development :: Libraries :: Python Modules
Classifier: License :: OSI Approved :: MIT License
Classifier: Programming Language :: Python :: 2.6
Classifier: Programming Language :: Python :: 2.7
Classifier: Programming Language :: Python :: 3
Requires: django
Requires: PyCryptodome
